{"data":{"site":{"siteMetadata":{"title":"warizz.io","author":"Warizz Yutanan"}},"markdownRemark":{"id":"a008419f-9f5f-5470-b6f8-4c24c7cbafec","excerpt":"Source  Why It’s Important to Feel Bad You don’t build psychological resilience by feeling good all the time, you build psychological resilience by getting good…","fields":{"slug":"/why-it-is-so-important-to-feel-bad-en/"},"html":"<p>Source <a href=\"https://youtu.be/c3uoyCNIa5c\">Why It’s Important to Feel Bad</a></p>\n<blockquote>\n<p>You don’t build psychological resilience by feeling good all the time, you build psychological resilience by getting good at feeling bad.</p>\n</blockquote>\n<p>Mark Manson pointed out that we will be more fragile if we handle the bad feeling by avoiding them. For me, how we confronting anxiety is a skill which we will be bad at it at first but we will get better if we practice more.</p>\n<blockquote>\n<p>Learning how to exist and be productive and do good things and be nice to people despite the fact that you feel like shit. The problem isn’t that you feel like shit, the problem is that you behave like shit and blame it on your feeling.</p>\n</blockquote>\n<p>I really like the paragraph. I want to print and put it on my wall or set it as my phone’s wallpaper as a reminder when I’m not feeling good that I should behave like normal in any situation.</p>\n<p>Not only the sadness, but I think I can use this principle for all other unpleasant feelings like anger, worry, or excitement.</p>","frontmatter":{"title":"Why It's Important to Feel Bad","date":"April 04, 2021","lang":null,"langs":null}}},"pageContext":{"slug":"/why-it-is-so-important-to-feel-bad-en/","previous":{"fields":{"slug":"/comic/snail/"},"frontmatter":{"title":"The snail","lang":null}},"next":null}}